MANIFEST.in
README.md
setup.py
/home/vsts/work/1/s/castar/src/Node.cpp
/home/vsts/work/1/s/castar/src/castar.cpp
/home/vsts/work/1/s/castar/src/distance.cpp
/home/vsts/work/1/s/castar/src/field.cpp
/home/vsts/work/1/s/castar/src/main.cpp
/home/vsts/work/1/s/castar/src/test.cpp
castar/src/Coordinates.hpp
castar/src/Node.cpp
castar/src/Node.hpp
castar/src/castar.cpp
castar/src/castar.hpp
castar/src/debug.hpp
castar/src/distance.cpp
castar/src/distance.hpp
castar/src/error.hpp
castar/src/field.cpp
castar/src/field.hpp
castar/src/main.cpp
castar/src/test.cpp
castar/src/test.hpp
castar/src/pybind11/LICENSE
castar/src/pybind11/README.md
castar/src/pybind11/attr.h
castar/src/pybind11/buffer_info.h
castar/src/pybind11/cast.h
castar/src/pybind11/chrono.h
castar/src/pybind11/common.h
castar/src/pybind11/complex.h
castar/src/pybind11/eigen.h
castar/src/pybind11/embed.h
castar/src/pybind11/eval.h
castar/src/pybind11/functional.h
castar/src/pybind11/iostream.h
castar/src/pybind11/numpy.h
castar/src/pybind11/operators.h
castar/src/pybind11/options.h
castar/src/pybind11/pybind11.h
castar/src/pybind11/pytypes.h
castar/src/pybind11/stl.h
castar/src/pybind11/stl_bind.h
castar/src/pybind11/detail/class.h
castar/src/pybind11/detail/common.h
castar/src/pybind11/detail/descr.h
castar/src/pybind11/detail/init.h
castar/src/pybind11/detail/internals.h
castar/src/pybind11/detail/typeid.h
pypath/__init__.py
pypath_fpa.egg-info/PKG-INFO
pypath_fpa.egg-info/SOURCES.txt
pypath_fpa.egg-info/dependency_links.txt
pypath_fpa.egg-info/requires.txt
pypath_fpa.egg-info/top_level.txt