Metadata-Version: 2.1
Name: pypath-fpa
Version: 0.2.9
Summary: Fast Pathfinding Algorithm
Home-page: https://github.com/bcluzel/pypath
Author: Baptiste CLUZEL
Author-email: baptiste.clu@gmail.com
License: UNKNOWN
Project-URL: Bug Reports, https://github.com/bcluzel/pypath/issues
Project-URL: Source, https://github.com/bcluzel/pypath
Keywords: pathfinding fast astar A* a*
Platform: UNKNOWN
Classifier: Development Status :: 5 - Production/Stable
Classifier: Intended Audience :: Developers
Classifier: Topic :: Scientific/Engineering :: GIS
Classifier: License :: OSI Approved :: GNU General Public License v3 (GPLv3)
Classifier: Programming Language :: Python :: 3
Requires-Python: >=3.5
